# synchronized
## 原理
JVM通过进入和退出monitor对象来控制sync的加锁与释放

```java
public class SycnDemo {
    public SycnDemo() {
    }

    public synchronized void method() {
        System.out.println("方法体");
    }

    public static synchronized void staticMethod() {
        System.out.println("静态方法体");
    }

    public void blockMethod() {
        synchronized(this) {
            System.out.println("方法块");
        }
    }
}

```
经过`javap -c -v -p`反汇编后
```shell script
$ javap -c -p  -v SycnDemo.class
Classfile /C:/Users/LuanMingYI/IdeaProjects/javaee/out/production/javaee/threadtest/SycnDemo.class
  Last modified 2020-6-29; size 792 bytes
  MD5 checksum 46c21e9f3721c9dadcb9b6d8a06db278
  Compiled from "SycnDemo.java"
public class threadtest.SycnDemo
  minor version: 0
  major version: 52
  flags: ACC_PUBLIC, ACC_SUPER
Constant pool:
{

  public synchronized void method();
    descriptor: ()V
    flags: ACC_PUBLIC, ACC_SYNCHRONIZED // ***********
    Code:
      stack=2, locals=1, args_size=1
         0: getstatic     #2                  // Field java/lang/System.out:Ljava/io/PrintStream;
         3: ldc           #3                  // String ▒▒▒▒▒▒
         5: invokevirtual #4                  // Method java/io/PrintStream.println:(Ljava/lang/String;)V
         8: return
      LineNumberTable:
        line 12: 0
        line 14: 8
      LocalVariableTable:
        Start  Length  Slot  Name   Signature
            0       9     0  this   Lthreadtest/SycnDemo;

  public static synchronized void staticMethod();
    descriptor: ()V
    flags: ACC_PUBLIC, ACC_STATIC, ACC_SYNCHRONIZED  // ***********
    Code:
      stack=2, locals=0, args_size=0
         0: getstatic     #2                  // Field java/lang/System.out:Ljava/io/PrintStream;
         3: ldc           #5                  // String ▒▒̬▒▒▒▒▒▒
         5: invokevirtual #4                  // Method java/io/PrintStream.println:(Ljava/lang/String;)V
         8: return
      LineNumberTable:
        line 18: 0
        line 20: 8

  public void blockMethod();
    descriptor: ()V
    flags: ACC_PUBLIC
    Code:
      stack=2, locals=3, args_size=1
         0: aload_0
         1: dup
         2: astore_1
         3: monitorenter    // ***********
         4: getstatic     #2                  // Field java/lang/System.out:Ljava/io/PrintStream;
         7: ldc           #6                  // String ▒▒▒▒▒▒
         9: invokevirtual #4                  // Method java/io/PrintStream.println:(Ljava/lang/String;)V
        12: aload_1
        13: monitorexit    // ***********
        14: goto          22
        17: astore_2
        18: aload_1
        19: monitorexit
        20: aload_2
        21: athrow
        22: return

}
SourceFile: "SycnDemo.java"

```

我们发现对方法体加sync关键字，在指令里没有`monitorenter`，`monitorexit`，而是多了一个`ACC_SYNCHRONIZED`关键字，这个关键字隐式调用了`monitor`

而monitor监视器源码是C++写的，在虚拟机的ObjectMonitor.hpp文件中。

每个对象有一个monitor。当monitor被占有时就会处于锁定状态，线程执行到Monitorenter指令时尝试获取monitor的所有权：

（1）如果monitor的进入数为0，那么该线程就会进入monitor，然后将进入数置为1，从而该线程即占有了monitor。

（2）如果该线程已经占有该monitor，重新进入会使monitor的进入数加1。

（3）并且执行monitorexit的线程肯定是monitor的持有者。当monitorexit指令执行时，monitor的进入数减1，如果进入数变为0，占有锁的线程就会退出monitor，不再是这个monitor的持有者。

（4）如果其他线程已经占有了monitor，那么这个线程就会进入阻塞状态，直到monitor的进入数为0，才会尝试去获取monitor的所有权。


## 储存地点

虚拟机中一个对象包括 对象头，实例数据，对其填充

synchronized用的锁是存在Java对象头里的

- Mark Word（标记字段）：默认存储对象的HashCode，分代年龄和锁标志位信息。它会根据对象的状态复用自己的存储空间，也就是说在运行期间Mark Word里存储的数据会随着锁标志位的变化而变化。
- Klass Point（类型指针）：对象指向它的类元数据的指针，虚拟机通过这个指针来确定这个对象是哪个类的实例。


## 锁优化与升级

阻塞或唤醒一个Java线程需要操作系统切换CPU状态来完成，这种状态转换需要耗费处理器时间。如果同步代码块中的内容过于简单，状态转换消耗的时间有可能比用户代码执行的时间还要长。这种方式就是synchronized最初实现同步的方式，这就是JDK 6之前synchronized效率低的原因。这种依赖于操作系统Mutex Lock所实现的锁我们称之为“重量级锁”，JDK 6中为了减少获得锁和释放锁带来的性能消耗，引入了“偏向锁”和“轻量级锁”。

所以目前锁一共有4种状态，级别从低到高依次是：无锁、偏向锁、轻量级锁和重量级锁。锁状态只能升级不能降级。

四种锁状态对应的的Mark Word内容如下：


| 锁状态 | 存储内容	| 标志位 |
|----------------|-----------------|-------|
|无锁	|对象的hashCode、对象分代年龄、是否是偏向锁（0）|	01|
|偏向锁|	偏向线程ID、偏向时间戳、对象分代年龄、是否是偏向锁（1）|	01|
|轻量级锁|	指向栈中锁记录的指针|	00|
|重量级锁|	指向互斥量（重量级锁）的指针|	10|


**无锁**

无锁没有对资源进行锁定，所有的线程都能访问并修改同一个资源，但同时只有一个线程能修改成功。

无锁的特点就是修改操作在循环内进行，线程会不断的尝试修改共享资源。如果没有冲突就修改成功并退出，否则就会继续循环尝试。如果有多个线程修改同一个值，必定会有一个线程能修改成功，而其他修改失败的线程会不断重试直到修改成功。CAS即是无锁的实现。无锁无法全面代替有锁，但无锁在某些场合下的性能是非常高的。

**偏向锁**

偏向锁是指一段同步代码一直被一个线程所访问，那么该线程会自动获取锁，降低获取锁的代价。

在大多数情况下，锁总是由同一线程多次获得，不存在多线程竞争，所以出现了偏向锁。其目标就是在只有一个线程执行同步代码块时能够提高性能。

当一个线程访问同步代码块并获取锁时，会在Mark Word里存储锁偏向的线程ID。在线程进入和退出同步块时不再通过CAS操作来加锁和解锁，而是检测Mark Word里是否存储着指向当前线程的偏向锁。引入偏向锁是为了在无多线程竞争的情况下尽量减少不必要的轻量级锁执行路径，因为轻量级锁的获取及释放依赖多次CAS原子指令，而偏向锁只需要在置换ThreadID的时候依赖一次CAS原子指令即可。

偏向锁只有遇到其他线程尝试竞争偏向锁时，持有偏向锁的线程才会释放锁，线程不会主动释放偏向锁。偏向锁的撤销，需要等待全局安全点（在这个时间点上没有字节码正在执行），它会首先暂停拥有偏向锁的线程，判断锁对象是否处于被锁定状态。撤销偏向锁后恢复到无锁（标志位为“01”）或轻量级锁（标志位为“00”）的状态。

偏向锁在JDK 6及以后的JVM里是默认启用的。可以通过JVM参数关闭偏向锁：-XX:-UseBiasedLocking=false，关闭之后程序默认会进入轻量级锁状态。

**轻量级锁**

是指当锁是偏向锁的时候，被另外的线程所访问，偏向锁就会升级为轻量级锁，其他线程会通过自旋的形式尝试获取锁，不会阻塞，从而提高性能。

在代码进入同步块的时候，如果同步对象锁状态为无锁状态（锁标志位为“01”状态，是否为偏向锁为“0”），虚拟机首先将在当前线程的栈帧中建立一个名为锁记录（Lock Record）的空间，用于存储锁对象目前的Mark Word的拷贝，然后拷贝对象头中的Mark Word复制到锁记录中。

拷贝成功后，虚拟机将使用CAS操作尝试将对象的Mark Word更新为指向Lock Record的指针，并将Lock Record里的owner指针指向对象的Mark Word。

如果这个更新动作成功了，那么这个线程就拥有了该对象的锁，并且对象Mark Word的锁标志位设置为“00”，表示此对象处于轻量级锁定状态。

如果轻量级锁的更新操作失败了，虚拟机首先会检查对象的Mark Word是否指向当前线程的栈帧，如果是就说明当前线程已经拥有了这个对象的锁，那就可以直接进入同步块继续执行，否则说明多个线程竞争锁。

若当前只有一个等待线程，则该线程通过自旋进行等待。但是当自旋超过一定的次数，或者一个线程在持有锁，一个在自旋，又有第三个来访时，轻量级锁升级为重量级锁。

**重量级锁**

升级为重量级锁时，锁标志的状态值变为“10”，此时Mark Word中存储的是指向重量级锁的指针，此时等待锁的线程都会进入阻塞状态。

重量级锁通过对象内部的监视器(monitor)实现，其中monitor的本质是依赖于底层操作系统的Mutex Lock实现，操作系统实现线程之间的切换需要从用户态到内核态的切换，切换成本非常高。

总结

偏向锁通过对比Mark Word解决加锁问题，避免多次执行CAS操作。而轻量级锁是通过用CAS操作和自旋来解决加锁问题，避免线程阻塞和唤醒而影响性能。重量级锁是将除了拥有锁的线程以外的线程都阻塞。

## lock 与 sync
- synchronized是关键字，是JVM层面的底层啥都帮我们做了，而Lock是一个接口，是JDK层面的有丰富的API。
- synchronized会自动释放锁，而Lock必须手动释放锁。
- synchronized是不可中断的，Lock可以中断也可以不中断。
- 通过Lock可以知道线程有没有拿到锁，而synchronized不能。
- synchronized能锁住方法和代码块，而Lock只能锁住代码块。
- Lock可以使用读锁提高多线程读效率。
- synchronized是非公平锁，ReentrantLock可以控制是否是公平锁。

